Metadata-Version: 2.1
Name: tempgit
Version: 0.0.17
Summary: Some temporal operations over git repositories using, mainly, ssh private keys.
Home-page: https://github.com/jmgomezsoriano/tempgit
Author: José Manuel Gómez Soriano
Author-email: jmgomez.soriano@gmail.com
License: LGPL2
Classifier: Programming Language :: Python :: 3
Classifier: License :: OSI Approved :: MIT License
Classifier: Operating System :: OS Independent
Requires-Python: >=3.7,<=3.8
License-File: LICENSE
